Aries/__init__.py
Aries/collections.py
Aries/command.py
Aries/db.py
Aries/docker.py
Aries/excel.py
Aries/files.py
Aries/oauth.py
Aries/outputs.py
Aries/strings.py
Aries/table.py
Aries/tasks.py
Aries/test.py
Aries/utils.py
Aries/web.py
Aries/Google/__init__.py
Aries/Google/drive.py
Aries/assets/file_signatures.json
Aries/assets/file_signatures_addon.json
Aries/gcp/__init__.py
Aries/gcp/logging.py
Aries/gcp/utils.py
Aries/gcp/vision.py
Aries/storage/__init__.py
Aries/storage/base.py
Aries/storage/cloud.py
Aries/storage/file.py
Aries/storage/gs.py
Aries/storage/io.py
Aries/storage/s3.py
Aries/storage/web.py
Aries/tests/__init__.py
Aries/tests/atest_collections.py
Aries/tests/atest_docker.py
Aries/tests/atest_excel.py
Aries/tests/atest_files.py
Aries/tests/atest_google_drive.py
Aries/tests/atest_outputs.py
Aries/tests/atest_storage.py
Aries/tests/atest_storage_cross.py
Aries/tests/atest_storage_gcp.py
Aries/tests/atest_storage_web.py
Aries/tests/atest_strings.py
Aries/tests/atest_tasks.py
Aries/tests/atest_web.py
Aries/tests/xtest_storage_aws.py
Aries/visual/__init__.py
Aries/visual/plotly.py
Aries_Python-0.1.330.dist-info/METADATA
Aries_Python-0.1.330.dist-info/WHEEL
Aries_Python-0.1.330.dist-info/top_level.txt
Aries_Python-0.1.330.dist-info/RECORD
